README.md
setup.py
mindmap_etl/__init__.py
mindmap_etl/extractor.py
mindmap_etl/schema_parse.py
mindmap_etl.egg-info/PKG-INFO
mindmap_etl.egg-info/SOURCES.txt
mindmap_etl.egg-info/dependency_links.txt
mindmap_etl.egg-info/not-zip-safe
mindmap_etl.egg-info/requires.txt
mindmap_etl.egg-info/top_level.txt
mindmap_etl/connector/__init__.py
mindmap_etl/connector/hugegraph.py
mindmap_etl/connector/pandas.py